{
	"format_version": "1.8.0",
	"animations": {
		"animation.wendigo.idle": {
			"loop": true,
			"animation_length": 4,
			"bones": {
				"Body": {
					"position": {
						"0.0": {
							"vector": [0, 0, 0]
						},
						"2.0": {
							"vector": [0, -3, 0]
						},
						"4.0": {
							"vector": [0, 0, 0]
						}
					}
				},
				"Left_Arm": {
					"position": {
						"0.0": {
							"vector": [0, 0, 3]
						},
						"2.0": {
							"vector": [0, -2, 1]
						},
						"4.0": {
							"vector": [0, 0, 3]
						}
					}
				},
				"cube_r3_r1": {
					"rotation": {
						"0.0": {
							"vector": [2.5, 0, 0]
						},
						"2.0": {
							"vector": [-12.5, 0, 0]
						},
						"4.0": {
							"vector": [2.5, 0, 0]
						}
					},
					"position": {
						"0.0": {
							"vector": [0, 0, 0]
						},
						"2.0": {
							"vector": [0, 2, -2]
						},
						"4.0": {
							"vector": [0, 0, 0]
						}
					}
				},
				"Left_Claw": {
					"rotation": {
						"0.0": {
							"vector": [2.5, 0, 0]
						},
						"2.0": {
							"vector": [-7.5, 0, 0]
						},
						"4.0": {
							"vector": [2.5, 0, 0],
							"easing": "linear"
						}
					},
					"position": {
						"0.0": {
							"vector": [0, 1, 0]
						},
						"2.0": {
							"vector": [0, 2, -4]
						},
						"4.0": {
							"vector": [0, 1, 0],
							"easing": "linear"
						}
					}
				},
				"Head": {
					"rotation": {
						"0.0": {
							"vector": [-5, 0, 0]
						},
						"2.0": {
							"vector": [5, 0, 0]
						},
						"4.0": {
							"vector": [-5, 0, 0]
						}
					},
					"position": {
						"0.0": {
							"vector": [0, -1, -2]
						},
						"2.0": {
							"vector": [0, -1, 10]
						},
						"4.0": {
							"vector": [0, -1, -2]
						}
					}
				},
				"Hips": {
					"rotation": {
						"0.0": {
							"vector": [-2.5, 0, 0]
						},
						"2.0": {
							"vector": [12.5, 0, 0]
						},
						"4.0": {
							"vector": [-2.5, 0, 0]
						}
					}
				},
				"Chest": {
					"rotation": {
						"0.0": {
							"vector": [-2.5, 0, 0]
						},
						"2.0": {
							"vector": [5, 0, 0]
						},
						"4.0": {
							"vector": [-2.5, 0, 0]
						}
					}
				},
				"Neck": {
					"rotation": {
						"0.0": {
							"vector": [-5, 0, 0]
						},
						"2.0": {
							"vector": [2.5, 0, 0]
						},
						"4.0": {
							"vector": [-5, 0, 0]
						}
					},
					"position": {
						"0.0": {
							"vector": [0, 1, 0]
						},
						"2.0": {
							"vector": [0, -1, -2]
						},
						"4.0": {
							"vector": [0, 1, 0]
						}
					}
				},
				"Arms": {
					"rotation": {
						"0.0": {
							"vector": [-15, 0, 0]
						},
						"4.0": {
							"vector": [-15, 0, 0]
						}
					},
					"position": {
						"0.0": {
							"vector": [0, -1, -8]
						},
						"2.0": {
							"vector": [0, 0, -3]
						},
						"4.0": {
							"vector": [0, -1, -8]
						}
					}
				},
				"cube_r2_r1": {
					"rotation": {
						"0.0": {
							"vector": [2.5, 0, 0]
						},
						"2.0": {
							"vector": [-12.5, 0, 0]
						},
						"4.0": {
							"vector": [2.5, 0, 0]
						}
					},
					"position": {
						"0.0": {
							"vector": [0, 0, 3]
						},
						"2.0": {
							"vector": [0, 0, -1]
						},
						"4.0": {
							"vector": [0, 0, 3]
						}
					}
				},
				"cube_r1_r1": {
					"rotation": {
						"0.0": {
							"vector": [0, 0, 0]
						},
						"2.0": {
							"vector": [0, 0, 0]
						},
						"4.0": {
							"vector": [0, 0, 0]
						}
					},
					"position": {
						"0.0": {
							"vector": [0, 0, 3]
						},
						"2.0": {
							"vector": [0, -2, 1]
						},
						"4.0": {
							"vector": [0, 0, 3]
						}
					}
				},
				"Claws_r1": {
					"rotation": {
						"0.0": {
							"vector": [0, 0, 0]
						},
						"2.0": {
							"vector": [-35, 0, 0]
						},
						"4.0": {
							"vector": [0, 0, 0]
						}
					},
					"position": {
						"0.0": {
							"vector": [0, 0, 3]
						},
						"2.0": {
							"vector": [0, -5, -1]
						},
						"4.0": {
							"vector": [0, 0, 3]
						}
					}
				},
				"Hands_r1": {
					"rotation": {
						"0.0": {
							"vector": [2.5, 0, 0]
						},
						"2.0": {
							"vector": [-27.5, 0, 0]
						},
						"4.0": {
							"vector": [2.5, 0, 0]
						}
					},
					"position": {
						"0.0": {
							"vector": [0, 0, 3]
						},
						"2.0": {
							"vector": [0, -2, 1]
						},
						"4.0": {
							"vector": [0, 0, 3]
						}
					}
				},
				"Torso": {
					"position": {
						"0.0": {
							"vector": [0, -1, 2]
						},
						"2.0": {
							"vector": [0, -1, 7]
						},
						"4.0": {
							"vector": [0, -1, 2]
						}
					}
				},
				"Right_Hoof": {
					"position": {
						"0.0": {
							"vector": [0, 0, 0]
						},
						"2.0": {
							"vector": [0, 3, 0]
						},
						"4.0": {
							"vector": [0, 0, 0]
						}
					}
				},
				"UpperLegs_r1": {
					"rotation": {
						"0.0": {
							"vector": [0, 0, 0]
						},
						"2.0": {
							"vector": [-17.5, 0, 0]
						},
						"4.0": {
							"vector": [0, 0, 0]
						}
					},
					"position": {
						"0.0": {
							"vector": [0, -1, 0]
						},
						"2.0": {
							"vector": [0, 1, 4]
						},
						"4.0": {
							"vector": [0, -1, 0]
						}
					}
				},
				"Knees_r1": {
					"rotation": {
						"0.0": {
							"vector": [0, 0, 0]
						},
						"2.0": {
							"vector": [-17.5, 0, 0]
						},
						"4.0": {
							"vector": [0, 0, 0]
						}
					},
					"position": {
						"0.0": {
							"vector": [0, 0, 0]
						},
						"2.0": {
							"vector": [0, 2, 2]
						},
						"4.0": {
							"vector": [0, 0, 0]
						}
					}
				},
				"LowerLegs_r1": {
					"rotation": {
						"0.0": {
							"vector": [-2.5, 0, 0]
						},
						"2.0": {
							"vector": [-12.5, 0, 0]
						},
						"4.0": {
							"vector": [-2.5, 0, 0]
						}
					},
					"position": {
						"0.0": {
							"vector": [0, 0, 0]
						},
						"2.0": {
							"vector": [0, 2, 1]
						},
						"4.0": {
							"vector": [0, 0, 0]
						}
					}
				},
				"UpperLegs_r2": {
					"rotation": {
						"0.0": {
							"vector": [-2.5, 0, 0]
						},
						"2.0": {
							"vector": [-17.5, 0, 0]
						},
						"4.0": {
							"vector": [-2.5, 0, 0]
						}
					},
					"position": {
						"0.0": {
							"vector": [0, -1, 0]
						},
						"2.0": {
							"vector": [0, 1, 4]
						},
						"4.0": {
							"vector": [0, -1, 0]
						}
					}
				},
				"Knees_r2": {
					"rotation": {
						"0.0": {
							"vector": [-2.5, 0, 0]
						},
						"2.0": {
							"vector": [-17.5, 0, 0]
						},
						"4.0": {
							"vector": [-2.5, 0, 0]
						}
					},
					"position": {
						"0.0": {
							"vector": [0, 0, 0]
						},
						"2.0": {
							"vector": [0, 2, 2]
						},
						"4.0": {
							"vector": [0, 0, 0]
						}
					}
				},
				"LowerLegs_r2": {
					"rotation": {
						"0.0": {
							"vector": [-2.5, 0, 0]
						},
						"2.0": {
							"vector": [-15, 0, 0]
						},
						"4.0": {
							"vector": [-2.5, 0, 0]
						}
					},
					"position": {
						"0.0": {
							"vector": [0, 0, 0]
						},
						"2.0": {
							"vector": [0, 2, 1]
						},
						"4.0": {
							"vector": [0, 0, 0]
						}
					}
				},
				"Left_Hoof": {
					"position": {
						"0.0": {
							"vector": [0, 0, 0]
						},
						"2.0": {
							"vector": [0, 3, 0]
						},
						"4.0": {
							"vector": [0, 0, 0]
						}
					}
				},
				"Right_Claw": {
					"rotation": {
						"0.0": {
							"vector": [0, 0, 0]
						},
						"2.0": {
							"vector": [22.5, 0, 0]
						},
						"4.0": {
							"vector": [0, 0, 0]
						}
					},
					"position": {
						"0.0": {
							"vector": [0, 0, 1]
						},
						"2.0": {
							"vector": [0, 11, -2]
						},
						"4.0": {
							"vector": [0, 0, 1]
						}
					}
				},
				"Hoof_r2": {
					"position": {
						"0.0": {
							"vector": [0, 0, 0]
						},
						"2.0": {
							"vector": [0, 3, 0]
						},
						"4.0": {
							"vector": [0, 0, 0]
						}
					}
				},
				"Hoof_r1": {
					"position": {
						"0.0": {
							"vector": [0, 0, 0]
						},
						"2.0": {
							"vector": [0, 3, 0]
						},
						"4.0": {
							"vector": [0, 0, 0]
						}
					}
				}
			}
		},
		"animation.wendigo.walk": {
			"loop": true,
			"animation_length": 2,
			"bones": {
				"Arms": {
					"position": {
						"vector": [0, -7, 2]
					}
				},
				"Right_Arm": {
					"position": {
						"vector": [0, -2, -4]
					}
				},
				"cube_r2_r1": {
					"rotation": {
						"0.0": {
							"vector": [-30, 0, 0]
						},
						"0.8": {
							"vector": [-2.5, 0, 0]
						},
						"1.2": {
							"vector": [-2.5, 0, 0]
						},
						"2.0": {
							"vector": [-30, 0, 0]
						}
					},
					"position": {
						"0.0": {
							"vector": [0, 8, -1]
						},
						"0.8": {
							"vector": [0, 7, 1]
						},
						"1.2": {
							"vector": [0, 7, 1]
						},
						"2.0": {
							"vector": [0, 8, -1]
						}
					}
				},
				"cube_r1_r1": {
					"rotation": {
						"0.0": {
							"vector": [10, 0, 0]
						},
						"0.8": {
							"vector": [-25, 0, 0]
						},
						"1.2": {
							"vector": [-25, 0, 0]
						},
						"2.0": {
							"vector": [10, 0, 0]
						}
					},
					"position": {
						"0.0": {
							"vector": [0, 2, 3]
						},
						"0.8": {
							"vector": [0, 5, 5]
						},
						"1.2": {
							"vector": [0, 5, 5]
						},
						"2.0": {
							"vector": [0, 2, 3]
						}
					}
				},
				"Right_Claw": {
					"rotation": {
						"0.0": {
							"vector": [-22.5, 0, 0]
						},
						"0.8": {
							"vector": [-5, 0, 0]
						},
						"1.2": {
							"vector": [-5, 0, 0]
						},
						"2.0": {
							"vector": [-22.5, 0, 0]
						}
					},
					"position": {
						"0.0": {
							"vector": [0, 8, -7]
						},
						"0.8": {
							"vector": [0, 6, 0]
						},
						"1.2": {
							"vector": [0, 6, 0]
						},
						"2.0": {
							"vector": [0, 8, -7]
						}
					}
				},
				"Left_Arm": {
					"position": {
						"vector": [0, -2, -4]
					}
				},
				"cube_r3_r1": {
					"rotation": {
						"0.0": {
							"vector": [-30, 0, 0]
						},
						"0.84": {
							"vector": [-2.5, 0, 0]
						},
						"1.2": {
							"vector": [-2.5, 0, 0]
						},
						"2.0": {
							"vector": [-30, 0, 0]
						}
					},
					"position": {
						"0.0": {
							"vector": [0, 8, -1]
						},
						"0.84": {
							"vector": [0, 7, 1]
						},
						"1.2": {
							"vector": [0, 7, 1]
						},
						"2.0": {
							"vector": [0, 8, -1]
						}
					}
				},
				"cube_r2_r2": {
					"rotation": {
						"0.0": {
							"vector": [10, 0, 0]
						},
						"0.84": {
							"vector": [-25, 0, 0]
						},
						"1.2": {
							"vector": [-25, 0, 0]
						},
						"2.0": {
							"vector": [10, 0, 0]
						}
					},
					"position": {
						"0.0": {
							"vector": [0, 2, 3]
						},
						"0.84": {
							"vector": [0, 5, 5]
						},
						"1.2": {
							"vector": [0, 5, 5]
						},
						"2.0": {
							"vector": [0, 2, 3]
						}
					}
				},
				"Left_Claw": {
					"rotation": {
						"0.0": {
							"vector": [-22.5, 0, 0]
						},
						"0.84": {
							"vector": [-5, 0, 0]
						},
						"1.2": {
							"vector": [-5, 0, 0]
						},
						"2.0": {
							"vector": [-22.5, 0, 0]
						}
					},
					"position": {
						"0.0": {
							"vector": [0, 8, -7]
						},
						"0.84": {
							"vector": [0, 6, 0]
						},
						"1.2": {
							"vector": [0, 6, 0]
						},
						"2.0": {
							"vector": [0, 8, -7]
						}
					}
				},
				"Head": {
					"rotation": {
						"0.0": {
							"vector": [12.5, 0, 0]
						},
						"0.68": {
							"vector": [-2.5, 0, 0]
						},
						"1.36": {
							"vector": [2.5, 0, 0]
						},
						"2.0": {
							"vector": [12.5, 0, 0]
						}
					},
					"position": {
						"0.0": {
							"vector": [0, -5, 9]
						},
						"0.68": {
							"vector": [0, -4, 2]
						},
						"1.36": {
							"vector": [0, -4, 8]
						},
						"2.0": {
							"vector": [0, -5, 9]
						}
					}
				},
				"Torso": {
					"rotation": {
						"0.0": {
							"vector": [12.5, 0, 0]
						},
						"1.32": {
							"vector": [0, 0, 0]
						},
						"2.0": {
							"vector": [12.5, 0, 0]
						}
					},
					"position": {
						"0.0": {
							"vector": [0, -5, 9]
						},
						"0.64": {
							"vector": [0, -2, 10]
						},
						"1.32": {
							"vector": [0, -4, 6]
						},
						"2.0": {
							"vector": [0, -5, 9]
						}
					}
				},
				"Hoof_r1": {
					"position": {
						"0.0": {
							"vector": [0, 0, 4.5]
						},
						"0.68": {
							"vector": [0, 5, 0]
						},
						"1.36": {
							"vector": [0, 0, -5],
							"easing": "linear"
						},
						"2.0": {
							"vector": [0, 0, 4.5]
						}
					}
				},
				"UpperLegs_r1": {
					"rotation": {
						"0.0": {
							"vector": [-5, 0, 0]
						},
						"0.68": {
							"vector": [-10, 0, 0]
						},
						"1.36": {
							"vector": [-25, 0, 0]
						},
						"2.0": {
							"vector": [-5, 0, 0]
						}
					},
					"position": {
						"0.0": {
							"vector": [0, 2, 1]
						},
						"0.68": {
							"vector": [0, 1, 4]
						},
						"1.36": {
							"vector": [0, -3, 2]
						},
						"2.0": {
							"vector": [0, 2, 1]
						}
					}
				},
				"Knees_r1": {
					"rotation": {
						"0.0": {
							"vector": [0, 0, 0]
						},
						"0.68": {
							"vector": [-10, 0, 0]
						},
						"1.36": {
							"vector": [-37.5, 0, 0]
						},
						"2.0": {
							"vector": [0, 0, 0]
						}
					},
					"position": {
						"0.0": {
							"vector": [0, 3, 1]
						},
						"0.68": {
							"vector": [0, 1, 4]
						},
						"1.36": {
							"vector": [0, -3, 0]
						},
						"2.0": {
							"vector": [0, 3, 1]
						}
					}
				},
				"LowerLegs_r1": {
					"rotation": {
						"0.0": {
							"vector": [25, 0, 0]
						},
						"0.68": {
							"vector": [-37.2, 0, 0]
						},
						"1.36": {
							"vector": [-29.6, 0, 0]
						},
						"2.0": {
							"vector": [25, 0, 0]
						}
					},
					"position": {
						"0.0": {
							"vector": [0, 1, 3]
						},
						"0.68": {
							"vector": [0, 2, 2.32]
						},
						"1.36": {
							"vector": [0, -2.36, -3.36]
						},
						"2.0": {
							"vector": [0, 1, 3]
						}
					}
				},
				"Hoof_r2": {
					"position": {
						"0.0": {
							"vector": [0, 0, -5]
						},
						"0.64": {
							"vector": [0, 0, 4.5]
						},
						"1.32": {
							"vector": [0, 5, 0]
						},
						"2.0": {
							"vector": [0, 0, -5]
						}
					}
				},
				"UpperLegs_r2": {
					"rotation": {
						"0.0": {
							"vector": [-25, 0, 0]
						},
						"0.64": {
							"vector": [-5, 0, 0]
						},
						"1.32": {
							"vector": [-10, 0, 0]
						},
						"2.0": {
							"vector": [-25, 0, 0]
						}
					},
					"position": {
						"0.0": {
							"vector": [0, -3, 2]
						},
						"0.64": {
							"vector": [0, 2, 1]
						},
						"1.32": {
							"vector": [0, 1, 4]
						},
						"2.0": {
							"vector": [0, -3, 2]
						}
					}
				},
				"Knees_r2": {
					"rotation": {
						"0.0": {
							"vector": [-37.5, 0, 0]
						},
						"0.64": {
							"vector": [0, 0, 0]
						},
						"1.32": {
							"vector": [-10, 0, 0]
						},
						"2.0": {
							"vector": [-37.5, 0, 0]
						}
					},
					"position": {
						"0.0": {
							"vector": [0, -3, 0]
						},
						"0.64": {
							"vector": [0, 3, 1]
						},
						"1.32": {
							"vector": [0, 1, 4]
						},
						"2.0": {
							"vector": [0, -3, 0]
						}
					}
				},
				"LowerLegs_r2": {
					"rotation": {
						"0.0": {
							"vector": [-29.6, 0, 0]
						},
						"0.64": {
							"vector": [25, 0, 0]
						},
						"1.32": {
							"vector": [-37.2, 0, 0]
						},
						"2.0": {
							"vector": [-29.6, 0, 0]
						}
					},
					"position": {
						"0.0": {
							"vector": [0, -2.36, -3.36]
						},
						"0.64": {
							"vector": [0, 1, 3]
						},
						"1.32": {
							"vector": [0, 2, 2.32]
						},
						"2.0": {
							"vector": [0, -2.36, -3.36]
						}
					}
				}
			}
		},
		"animation.wendigo.attack": {
			"loop": "hold_on_last_frame",
			"animation_length": 1,
			"bones": {
				"Arms": {
					"rotation": {
						"0.0": {
							"vector": [-10, 0, 0]
						},
						"0.44": {
							"vector": [-95, 0, 0],
							"easing": "easeOutBack"
						},
						"1.0": {
							"vector": [-10, 0, 0],
							"easing": "easeInBack"
						}
					},
					"position": {
						"0.0": {
							"vector": [0, 0, 1]
						},
						"0.44": {
							"vector": [0, 3, 5],
							"easing": "easeOutBack"
						},
						"1.0": {
							"vector": [0, 2, 5],
							"easing": "easeInBack"
						}
					}
				},
				"Head": {
					"rotation": {
						"0.0": {
							"vector": [0, 0, 0]
						},
						"0.52": {
							"vector": [-7.5, 0, 0],
							"easing": "easeOutBack"
						}
					}
				},
				"Torso": {
					"rotation": {
						"0.0": {
							"vector": [0, 0, 0]
						},
						"0.52": {
							"vector": [-7.5, 0, 0],
							"easing": "easeOutBack"
						}
					}
				}
			}
		}
	},
	"geckolib_format_version": 2
}